rpq/RpqLua.py
rpq/RpqQueue.py
rpq/__init__.py
rpq_src/__init__.py
rpq_src/__main__.py
rpq_src/queue_monitor.py
rpq_src/redis-priority-queue.lua
rpq-2.2.dist-info/LICENSE
rpq-2.2.dist-info/METADATA
rpq-2.2.dist-info/WHEEL
rpq-2.2.dist-info/entry_points.txt
rpq-2.2.dist-info/top_level.txt
rpq-2.2.dist-info/RECORD
